{"ENTITY_ID":7,"tables":[{"id":"822cfbf0-1a3d-4e46-9139-3fc8fc8812c6","position":{"x":84,"y":147},"data":{"table_name":"client","fields":[{"fieldName":"id","fieldType":3,"isPK":true,"isNotNull":false,"isUnique":false,"defaultValue":"","args":[1,1],"isAutoIncrement":true},{"fieldName":"nome","fieldType":10,"isPK":false,"isNotNull":true,"isUnique":false,"defaultValue":"","args":["512"],"isAutoIncrement":false}],"next_id":2,"checkName":[],"checkCondition":[]}},{"id":"76b59609-c04b-4655-a164-dc1e79c405b1","position":{"x":591,"y":54},"data":{"table_name":"client_payments","fields":[{"fieldName":"amount","fieldType":5,"isPK":false,"isNotNull":true,"isUnique":false,"defaultValue":"","args":"","isAutoIncrement":false}],"next_id":2,"checkName":[],"checkCondition":[]}},{"id":"62d95ed2-07f2-4232-8136-344cf732e663","position":{"x":590,"y":136},"data":{"table_name":"client_credits","fields":[{"fieldName":"amount","fieldType":5,"isPK":false,"isNotNull":true,"isUnique":false,"defaultValue":"","args":"","isAutoIncrement":false}],"next_id":1,"checkName":[],"checkCondition":[]}},{"id":"748848a9-720f-4ed1-8a80-6673bad111b5","position":{"x":580,"y":557},"data":{"table_name":"total_payments","fields":[{"fieldName":"id","fieldType":3,"isPK":true,"isNotNull":false,"isUnique":false,"defaultValue":"","args":"","isAutoIncrement":false},{"fieldName":"amount","fieldType":5,"isPK":false,"isNotNull":true,"isUnique":false,"defaultValue":"","args":"","isAutoIncrement":false}],"next_id":2,"checkName":[],"checkCondition":[]}},{"id":"2207b088-6e0e-4ae2-9c59-0a95dbf8be5b","position":{"x":578,"y":644},"data":{"table_name":"total_credits","fields":[{"fieldName":"id","fieldType":3,"isPK":true,"isNotNull":false,"isUnique":false,"defaultValue":"","args":[1,1],"isAutoIncrement":false},{"fieldName":"amount","fieldType":5,"isPK":false,"isNotNull":true,"isUnique":false,"defaultValue":"","args":"","isAutoIncrement":false}],"next_id":2,"checkName":[],"checkCondition":[]}},{"id":"727f45ff-4c6c-4243-9aeb-e8c50ba6343b","position":{"x":591,"y":226},"data":{"table_name":"balance","fields":[{"fieldName":"amount","fieldType":5,"isPK":false,"isNotNull":true,"isUnique":false,"defaultValue":"","args":"","isAutoIncrement":false}],"next_id":1,"checkName":[],"checkCondition":[]}},{"id":"2b4159e9-cb16-4910-9b45-30d36c18d3c0","position":{"x":592,"y":317},"data":{"table_name":"last_month_bill","fields":[{"fieldName":"amount","fieldType":5,"isPK":false,"isNotNull":true,"isUnique":false,"defaultValue":"","args":"","isAutoIncrement":false}],"next_id":1,"checkName":[],"checkCondition":[]}},{"id":"7972069b-1fe7-41fd-8021-7376c3c02bd5","position":{"x":84,"y":441},"data":{"table_name":"currency","fields":[{"fieldName":"name","fieldType":10,"isPK":true,"isNotNull":false,"isUnique":false,"defaultValue":"","args":"50","isAutoIncrement":false},{"fieldName":"conversion","fieldType":5,"isPK":false,"isNotNull":true,"isUnique":false,"defaultValue":"","args":"","isAutoIncrement":false}],"next_id":3,"checkName":[],"checkCondition":[]}}],"links":[{"source":"822cfbf0-1a3d-4e46-9139-3fc8fc8812c6","target":"76b59609-c04b-4655-a164-dc1e79c405b1","order":"normal","sourceCard":"1:1","targetCard":"0:n","label":"makes","hierType":null,"sourceisweak":false,"targetisweak":false},{"source":"822cfbf0-1a3d-4e46-9139-3fc8fc8812c6","target":"62d95ed2-07f2-4232-8136-344cf732e663","order":"normal","sourceCard":"1:1","targetCard":"0:n","label":"makes","hierType":null,"sourceisweak":false,"targetisweak":false},{"source":"822cfbf0-1a3d-4e46-9139-3fc8fc8812c6","target":"727f45ff-4c6c-4243-9aeb-e8c50ba6343b","order":"normal","sourceCard":"1:1","targetCard":"0:n","label":"has","hierType":null,"sourceisweak":false,"targetisweak":false},{"source":"822cfbf0-1a3d-4e46-9139-3fc8fc8812c6","target":"2b4159e9-cb16-4910-9b45-30d36c18d3c0","order":"normal","sourceCard":"1:1","targetCard":"0:n","label":"has","hierType":null,"sourceisweak":false,"targetisweak":false}],"normalization":1,"database":0}